{
  "id": "ep000310",
  "epid": "A15517",
  "particDesc": [
    {
      "sex": "FEMALE",
      "id": "London",
      "name": "London",
      "isGroup": false
    },
    {
      "sex": "MALE",
      "id": "policy",
      "name": "Policy",
      "isGroup": false
    },
    {
      "sex": "MALE",
      "id": "pleasure",
      "name": "Pleasure",
      "isGroup": false
    },
    {
      "sex": "MALE",
      "id": "pomp",
      "name": "Pomp",
      "isGroup": false
    },
    {
      "sex": "MALE",
      "id": "will",
      "name": "Will",
      "isGroup": false
    },
    {
      "sex": "MALE",
      "id": "wit",
      "name": "Wit",
      "isGroup": false
    },
    {
      "sex": "MALE",
      "id": "wealth",
      "name": "Wealth",
      "isGroup": false
    },
    {
      "sex": "MALE",
      "id": "simplicity",
      "name": "Simplicity",
      "isGroup": false
    },
    {
      "sex": "MALE",
      "id": "simony",
      "name": "Simony",
      "isGroup": false
    },
    {
      "sex": "FEMALE",
      "id": "penury",
      "name": "Penury",
      "isGroup": false
    },
    {
      "sex": "MALE",
      "id": "nemo",
      "name": "Nemo",
      "isGroup": false
    },
    {
      "sex": "MALE",
      "id": "fraud",
      "name": "Fraud",
      "isGroup": false
    },
    {
      "sex": "MALE",
      "id": "usury",
      "name": "Usury",
      "isGroup": false
    },
    {
      "sex": "MALE",
      "id": "dissimulation",
      "name": "Dissimulation",
      "isGroup": false
    },
    {
      "sex": "FEMALE",
      "id": "conscience",
      "name": "Conscience",
      "isGroup": false
    },
    {
      "sex": "FEMALE",
      "id": "love",
      "name": "Love",
      "isGroup": false
    },
    {
      "sex": "FEMALE",
      "id": "lucre",
      "name": "Lucre",
      "isGroup": false
    },
    {
      "sex": "MALE",
      "id": "sorrow",
      "name": "Sorrow",
      "isGroup": false
    },
    {
      "sex": "MALE",
      "id": "falsehood",
      "name": "Falsehood",
      "isGroup": false
    },
    {
      "sex": "MALE",
      "id": "industry",
      "name": "Industry",
      "isGroup": false
    },
    {
      "sex": "MALE",
      "id": "pure-zeal",
      "name": "Pure Zeal",
      "isGroup": false
    },
    {
      "sex": "MALE",
      "id": "sincerity",
      "name": "Sincerity",
      "isGroup": false
    },
    {
      "sex": "MALE",
      "id": "diligence",
      "name": "Diligence",
      "isGroup": false
    },
    {
      "sex": "MALE",
      "id": "fealty",
      "name": "Fealty",
      "isGroup": false
    },
    {
      "sex": "MALE",
      "id": "constable",
      "name": "Constable",
      "isGroup": false
    },
    {
      "sex": "MALE",
      "id": "pride",
      "name": "Pride",
      "isGroup": false
    },
    {
      "sex": "MALE",
      "id": "desire",
      "name": "Desire",
      "isGroup": false
    },
    {
      "sex": "MALE",
      "id": "delight",
      "name": "Delight",
      "isGroup": false
    },
    {
      "sex": "MALE",
      "id": "devotion",
      "name": "Devotion",
      "isGroup": false
    },
    {
      "sex": "MALE",
      "id": "double-dealing",
      "name": "Double Dealing",
      "isGroup": false
    }
  ],
  "speeches": {
    "A15517-e107650": [
      "fraud"
    ],
    "A15517-e103160": [
      "simplicity"
    ],
    "A15517-e118770": [
      "simplicity"
    ],
    "A15517-e108170": [
      "simplicity"
    ],
    "A15517-e101980": [
      "wit"
    ],
    "A15517-e124070": [
      "policy"
    ],
    "A15517-e105620": [
      "wealth"
    ],
    "A15517-e121550": [
      "pomp"
    ],
    "A15517-e112420": [
      "pomp"
    ],
    "A15517-e123970": [
      "dissimulation"
    ],
    "A15517-e114990": [
      "pomp"
    ],
    "A15517-e122380": [
      "pleasure"
    ],
    "A15517-e113780": [
      "pomp"
    ],
    "A15517-e109200": [
      "conscience"
    ],
    "A15517-e113950": [
      "simony"
    ],
    "A15517-e119300": [
      "fealty"
    ],
    "A15517-e108270": [
      "fraud"
    ],
    "A15517-e117370": [
      "usury"
    ],
    "A15517-e104370": [
      "simony"
    ],
    "A15517-e109160": [
      "love"
    ],
    "A15517-e125750": [
      "policy"
    ],
    "A15517-e106420": [
      "nemo"
    ],
    "A15517-e119930": [
      "wealth"
    ],
    "A15517-e110690": [
      "love"
    ],
    "A15517-e114470": [
      "pleasure"
    ],
    "A15517-e102690": [
      "will"
    ],
    "A15517-e100900": [
      "policy"
    ],
    "A15517-e112600": [
      "policy"
    ],
    "A15517-e123910": [
      "usury"
    ],
    "A15517-e110750": [
      "simplicity"
    ],
    "A15517-e111530": [
      "dissimulation"
    ],
    "A15517-e111070": [
      "lucre"
    ],
    "A15517-e115730": [
      "pleasure"
    ],
    "A15517-e105560": [
      "simony"
    ],
    "A15517-e118120": [
      "usury"
    ],
    "A15517-e112740": [
      "pleasure"
    ],
    "A15517-e106150": [
      "wit"
    ],
    "A15517-e102870": [
      "wealth"
    ],
    "A15517-e118190": [
      "fraud"
    ],
    "A15517-e103020": [
      "wealth"
    ],
    "A15517-e124850": [
      "policy"
    ],
    "A15517-e121960": [
      "pride"
    ],
    "A15517-e114670": [
      "pleasure"
    ],
    "A15517-e102490": [
      "wit"
    ],
    "A15517-e127000": [
      "pleasure"
    ],
    "A15517-e124920": [
      "simony"
    ],
    "A15517-e113170": [
      "falsehood"
    ],
    "A15517-e115140": [
      "conscience"
    ],
    "A15517-e112240": [
      "policy"
    ],
    "A15517-e107290": [
      "pomp"
    ],
    "A15517-e112890": [
      "pomp"
    ],
    "A15517-e108350": [
      "fraud"
    ],
    "A15517-e120920": [
      "fealty"
    ],
    "A15517-e122980": [
      "pomp"
    ],
    "A15517-e107960": [
      "simplicity"
    ],
    "A15517-e117410": [
      "usury"
    ],
    "A15517-e105240": [
      "wealth"
    ],
    "A15517-e124380": [
      "diligence"
    ],
    "A15517-e122250": [
      "policy"
    ],
    "A15517-e110670": [
      "dissimulation"
    ],
    "A15517-e126290": [
      "simony"
    ],
    "A15517-e126330": [
      "simplicity"
    ],
    "A15517-e101240": [
      "policy"
    ],
    "A15517-e109140": [
      "conscience"
    ],
    "A15517-e123170": [
      "nemo"
    ],
    "A15517-e103830": [
      "will"
    ],
    "A15517-e106910": [
      "policy"
    ],
    "A15517-e104190": [
      "wealth"
    ],
    "A15517-e110930": [
      "usury"
    ],
    "A15517-e105990": [
      "penury"
    ],
    "A15517-e114390": [
      "policy"
    ],
    "A15517-e105540": [
      "will"
    ],
    "A15517-e121640": [
      "pleasure"
    ],
    "A15517-e119850": [
      "pomp"
    ],
    "A15517-e125770": [
      "desire"
    ],
    "A15517-e125840": [
      "policy"
    ],
    "A15517-e124670": [
      "simplicity"
    ],
    "A15517-e109810": [
      "lucre"
    ],
    "A15517-e115590": [
      "policy"
    ],
    "A15517-e117550": [
      "simplicity"
    ],
    "A15517-e122160": [
      "pomp"
    ],
    "A15517-e109790": [
      "conscience"
    ],
    "A15517-e126010": [
      "desire"
    ],
    "A15517-e121770": [
      "pomp"
    ],
    "A15517-e113190": [
      "nemo"
    ],
    "A15517-e121810": [
      "fealty"
    ],
    "A15517-e119350": [
      "fealty"
    ],
    "A15517-e103700": [
      "will"
    ],
    "A15517-e118590": [
      "constable"
    ],
    "A15517-e114200": [
      "simplicity"
    ],
    "A15517-e103100": [
      "will"
    ],
    "A15517-e124200": [
      "policy"
    ],
    "A15517-e107050": [
      "policy"
    ],
    "A15517-e103660": [
      "wit"
    ],
    "A15517-e104910": [
      "will"
    ],
    "A15517-e115290": [
      "nemo"
    ],
    "A15517-e104310": [
      "wealth"
    ],
    "A15517-e102590": [
      "wit"
    ],
    "A15517-e111620": [
      "conscience"
    ],
    "A15517-e125110": [
      "diligence"
    ],
    "A15517-e109480": [
      "love"
    ],
    "A15517-e106080": [
      "penury"
    ],
    "A15517-e104630": [
      "will"
    ],
    "A15517-e107940": [
      "fraud"
    ],
    "A15517-e105520": [
      "simony"
    ],
    "A15517-e103290": [
      "will"
    ],
    "A15517-e117980": [
      "fraud"
    ],
    "A15517-e122540": [
      "pleasure"
    ],
    "A15517-e113130": [
      "falsehood"
    ],
    "A15517-e112260": [
      "pomp"
    ],
    "A15517-e104290": [
      "simony"
    ],
    "A15517-e101880": [
      "will"
    ],
    "A15517-e104010": [
      "wealth"
    ],
    "A15517-e117430": [
      "simplicity"
    ],
    "A15517-e120820": [
      "fealty"
    ],
    "A15517-e102530": [
      "wealth"
    ],
    "A15517-e119830": [
      "fealty"
    ],
    "A15517-e110590": [
      "love"
    ],
    "A15517-e125860": [
      "devotion"
    ],
    "A15517-e105260": [
      "simony"
    ],
    "A15517-e123890": [
      "policy"
    ],
    "A15517-e107180": [
      "nemo"
    ],
    "A15517-e123220": [
      "pomp"
    ],
    "A15517-e124770": [
      "pleasure"
    ],
    "A15517-e103680": [
      "simony"
    ],
    "A15517-e104330": [
      "simony"
    ],
    "A15517-e103740": [
      "wit"
    ],
    "A15517-e123620": [
      "pleasure"
    ],
    "A15517-e115010": [
      "policy"
    ],
    "A15517-e126390": [
      "dissimulation"
    ],
    "A15517-e103480": [
      "simony"
    ],
    "A15517-e110270": [
      "simplicity"
    ],
    "A15517-e123560": [
      "policy"
    ],
    "A15517-e124690": [
      "pomp"
    ],
    "A15517-e104950": [
      "will"
    ],
    "A15517-e118670": [
      "pleasure"
    ],
    "A15517-e127260": [
      "diligence"
    ],
    "A15517-e100820": [
      "pleasure"
    ],
    "A15517-e113240": [
      "policy"
    ],
    "A15517-e103120": [
      "wealth"
    ],
    "A15517-e107850": [
      "fraud"
    ],
    "A15517-e116770": [
      "policy"
    ],
    "A15517-e102360": [
      "wit"
    ],
    "A15517-e124980": [
      "fraud"
    ],
    "A15517-e116630": [
      "pleasure"
    ],
    "A15517-e115630": [
      "pomp"
    ],
    "A15517-e109340": [
      "conscience"
    ],
    "A15517-e127090": [
      "pleasure"
    ],
    "A15517-e102210": [
      "wealth"
    ],
    "A15517-e119170": [
      "fealty"
    ],
    "A15517-e118720": [
      "constable"
    ],
    "A15517-e115550": [
      "nemo"
    ],
    "A15517-e107670": [
      "usury"
    ],
    "A15517-e101050": [
      "pomp"
    ],
    "A15517-e101610": [
      "pleasure"
    ],
    "A15517-e117510": [
      "simplicity"
    ],
    "A15517-e124020": [
      "fraud"
    ],
    "A15517-e120840": [
      "policy"
    ],
    "A15517-e110310": [
      "simony"
    ],
    "A15517-e123990": [
      "usury"
    ],
    "A15517-e105440": [
      "will"
    ],
    "A15517-e122360": [
      "pomp"
    ],
    "A15517-e125940": [
      "delight"
    ],
    "A15517-e101340": [
      "pomp"
    ],
    "A15517-e119660": [
      "fealty"
    ],
    "A15517-e122400": [
      "policy"
    ],
    "A15517-e106780": [
      "nemo"
    ],
    "A15517-e104270": [
      "will"
    ],
    "A15517-e103140": [
      "will"
    ],
    "A15517-e101960": [
      "wealth"
    ],
    "A15517-e110870": [
      "conscience"
    ],
    "A15517-e105600": [
      "simplicity"
    ],
    "A15517-e104650": [
      "simony"
    ],
    "A15517-e117390": [
      "simplicity"
    ],
    "A15517-e104350": [
      "will"
    ],
    "A15517-e102550": [
      "wit"
    ],
    "A15517-e109180": [
      "lucre"
    ],
    "A15517-e125150": [
      "nemo"
    ],
    "A15517-e102850": [
      "will"
    ],
    "A15517-e112070": [
      "nemo"
    ],
    "A15517-e123240": [
      "lucre"
    ],
    "A15517-e103760": [
      "simony"
    ],
    "A15517-e111090": [
      "simplicity"
    ],
    "A15517-e108510": [
      "love"
    ],
    "A15517-e100420": [
      "London"
    ],
    "A15517-e105580": [
      "wit"
    ],
    "A15517-e113880": [
      "policy"
    ],
    "A15517-e118100": [
      "simony"
    ],
    "A15517-e104970": [
      "simony"
    ],
    "A15517-e118690": [
      "policy"
    ],
    "A15517-e127280": [
      "simplicity"
    ],
    "A15517-e114510": [
      "pomp"
    ],
    "A15517-e124750": [
      "simony"
    ],
    "A15517-e110610": [
      "simplicity"
    ],
    "A15517-e110900": [
      "fraud"
    ],
    "A15517-e115650": [
      "nemo"
    ],
    "A15517-e116610": [
      "policy"
    ],
    "A15517-e122290": [
      "pomp"
    ],
    "A15517-e115710": [
      "policy"
    ],
    "A15517-e125680": [
      "pleasure"
    ],
    "A15517-e109320": [
      "lucre"
    ],
    "A15517-e116270": [
      "policy"
    ],
    "A15517-e101900": [
      "wealth"
    ],
    "A15517-e102230": [
      "wit"
    ],
    "A15517-e119080": [
      "pomp"
    ],
    "A15517-e101850": [
      "wit"
    ],
    "A15517-e101160": [
      "will"
    ],
    "A15517-e103780": [
      "wit"
    ],
    "A15517-e123260": [
      "nemo"
    ],
    "A15517-e107810": [
      "simplicity"
    ],
    "A15517-e124730": [
      "policy"
    ],
    "A15517-e103640": [
      "simony"
    ],
    "A15517-e125660": [
      "policy"
    ],
    "A15517-e104790": [
      "wit"
    ],
    "A15517-e108660": [
      "lucre"
    ],
    "A15517-e121890": [
      "fealty"
    ],
    "A15517-e103580": [
      "wealth"
    ],
    "A15517-e115930": [
      "pleasure"
    ],
    "A15517-e126350": [
      "diligence"
    ],
    "A15517-e106890": [
      "pleasure"
    ],
    "A15517-e102750": [
      "wit"
    ],
    "A15517-e121110": [
      "fealty"
    ],
    "A15517-e104990": [
      "will"
    ],
    "A15517-e112970": [
      "double-dealing"
    ],
    "A15517-e112860": [
      "policy"
    ],
    "A15517-e106270": [
      "simony"
    ],
    "A15517-e109620": [
      "conscience"
    ],
    "A15517-e109910": [
      "simony"
    ],
    "A15517-e118570": [
      "policy"
    ],
    "A15517-e108990": [
      "lucre"
    ],
    "A15517-e110630": [
      "dissimulation"
    ],
    "A15517-e114900": [
      "pleasure"
    ],
    "A15517-e125700": [
      "policy"
    ],
    "A15517-e106560": [
      "nemo"
    ],
    "A15517-e109250": [
      "lucre"
    ],
    "A15517-e106240": [
      "wit"
    ],
    "A15517-e122900": [
      "love"
    ],
    "A15517-e102020": [
      "wealth"
    ],
    "A15517-e115480": [
      "conscience"
    ],
    "A15517-e112220": [
      "nemo"
    ],
    "A15517-e127420": [
      "policy"
    ],
    "A15517-e112300": [
      "nemo"
    ],
    "A15517-e117530": [
      "usury"
    ],
    "A15517-e117890": [
      "fraud"
    ],
    "A15517-e125000": [
      "diligence"
    ],
    "A15517-e118900": [
      "pleasure"
    ],
    "A15517-e101220": [
      "pleasure"
    ],
    "A15517-e122580": [
      "nemo"
    ],
    "A15517-e113030": [
      "conscience"
    ],
    "A15517-e101360": [
      "pleasure"
    ],
    "A15517-e101070": [
      "policy"
    ],
    "A15517-e124410": [
      "pomp"
    ],
    "A15517-e107770": [
      "dissimulation"
    ],
    "A15517-e102920": [
      "will"
    ],
    "A15517-e123430": [
      "policy"
    ],
    "A15517-e113330": [
      "double-dealing"
    ],
    "A15517-e118740": [
      "simplicity"
    ],
    "A15517-e105070": [
      "wit"
    ],
    "A15517-e104490": [
      "simony"
    ],
    "A15517-e125960": [
      "policy"
    ],
    "A15517-e126030": [
      "devotion"
    ],
    "A15517-e105420": [
      "simony"
    ],
    "A15517-e109280": [
      "conscience"
    ],
    "A15517-e102570": [
      "will"
    ],
    "A15517-e110550": [
      "simony"
    ],
    "A15517-e105360": [
      "wit"
    ],
    "A15517-e119010": [
      "policy"
    ],
    "A15517-e103310": [
      "simony"
    ],
    "A15517-e102040": [
      "wit"
    ],
    "A15517-e122720": [
      "lucre"
    ],
    "A15517-e104430": [
      "wealth"
    ],
    "A15517-e115610": [
      "pleasure"
    ],
    "A15517-e109360": [
      "lucre"
    ],
    "A15517-e124550": [
      "simony"
    ],
    "A15517-e108380": [
      "simplicity"
    ],
    "A15517-e118880": [
      "pomp"
    ],
    "A15517-e119200": [
      "fealty"
    ],
    "A15517-e109930": [
      "lucre"
    ],
    "A15517-e107830": [
      "simony"
    ],
    "A15517-e123930": [
      "dissimulation"
    ],
    "A15517-e111190": [
      "usury"
    ],
    "A15517-e117700": [
      "fraud"
    ],
    "A15517-e115750": [
      "conscience"
    ],
    "A15517-e121510": [
      "pride"
    ],
    "A15517-e125640": [
      "delight"
    ],
    "A15517-e125060": [
      "diligence"
    ],
    "A15517-e113050": [
      "nemo"
    ],
    "A15517-e101940": [
      "will"
    ],
    "A15517-e103040": [
      "will"
    ],
    "A15517-e118080": [
      "usury"
    ],
    "A15517-e101090": [
      "pomp"
    ],
    "A15517-e103950": [
      "wit"
    ],
    "A15517-e120800": [
      "policy"
    ],
    "A15517-e117350": [
      "simplicity"
    ],
    "A15517-e105400": [
      "will"
    ],
    "A15517-e116330": [
      "pomp"
    ],
    "A15517-e105380": [
      "simplicity"
    ],
    "A15517-e114010": [
      "penury"
    ],
    "A15517-e126450": [
      "fraud"
    ],
    "A15517-e112120": [
      "nemo"
    ],
    "A15517-e115450": [
      "pleasure"
    ],
    "A15517-e114690": [
      "pomp"
    ],
    "A15517-e104610": [
      "simony"
    ],
    "A15517-e112690": [
      "pomp"
    ],
    "A15517-e127110": [
      "fraud"
    ],
    "A15517-e124810": [
      "pleasure"
    ],
    "A15517-e125980": [
      "pleasure"
    ],
    "A15517-e106870": [
      "nemo"
    ],
    "A15517-e114730": [
      "pleasure"
    ],
    "A15517-e120310": [
      "pride"
    ],
    "A15517-e126170": [
      "simplicity"
    ],
    "A15517-e102100": [
      "wit"
    ],
    "A15517-e102610": [
      "will"
    ],
    "A15517-e112090": [
      "pleasure"
    ],
    "A15517-e105710": [
      "will"
    ],
    "A15517-e123950": [
      "usury"
    ],
    "A15517-e119960": [
      "will"
    ],
    "A15517-e117720": [
      "simony"
    ],
    "A15517-e105460": [
      "simony"
    ],
    "A15517-e118930": [
      "diligence"
    ],
    "A15517-e102060": [
      "wealth"
    ],
    "A15517-e115570": [
      "pleasure"
    ],
    "A15517-e120060": [
      "fealty"
    ],
    "A15517-e112040": [
      "pomp"
    ],
    "A15517-e111280": [
      "simplicity"
    ],
    "A15517-e124570": [
      "pomp"
    ],
    "A15517-e101030": [
      "pleasure"
    ],
    "A15517-e119220": [
      "fealty"
    ],
    "A15517-e106110": [
      "simony"
    ],
    "A15517-e124890": [
      "pomp"
    ],
    "A15517-e125900": [
      "delight"
    ],
    "A15517-e114630": [
      "pomp"
    ],
    "A15517-e107880": [
      "simplicity"
    ],
    "A15517-e124040": [
      "pomp"
    ],
    "A15517-e110710": [
      "dissimulation"
    ],
    "A15517-e104450": [
      "simony"
    ],
    "A15517-e115770": [
      "pleasure"
    ],
    "A15517-e121530": [
      "fealty"
    ],
    "A15517-e101920": [
      "wit"
    ],
    "A15517-e113650": [
      "sincerity"
    ],
    "A15517-e108210": [
      "fraud"
    ],
    "A15517-e125600": [
      "devotion"
    ],
    "A15517-e108230": [
      "simplicity"
    ],
    "A15517-e111300": [
      "lucre"
    ],
    "A15517-e114180": [
      "fraud"
    ],
    "A15517-e102650": [
      "will"
    ],
    "A15517-e114370": [
      "nemo"
    ],
    "A15517-e106930": [
      "pomp"
    ],
    "A15517-e104170": [
      "simony"
    ],
    "A15517-e104510": [
      "wit"
    ],
    "A15517-e124950": [
      "diligence"
    ],
    "A15517-e117270": [
      "pomp"
    ],
    "A15517-e111560": [
      "simplicity"
    ],
    "A15517-e117330": [
      "usury"
    ],
    "A15517-e117860": [
      "simony"
    ],
    "A15517-e125790": [
      "policy"
    ],
    "A15517-e109430": [
      "lucre"
    ],
    "A15517-e119630": [
      "pomp"
    ],
    "A15517-e110390": [
      "simplicity"
    ],
    "A15517-e106850": [
      "pomp"
    ],
    "A15517-e113990": [
      "simony"
    ],
    "A15517-e107320": [
      "nemo"
    ],
    "A15517-e126190": [
      "diligence"
    ],
    "A15517-e109650": [
      "fraud"
    ],
    "A15517-e121130": [
      "pomp"
    ],
    "A15517-e103600": [
      "simony"
    ],
    "A15517-e118550": [
      "simplicity"
    ],
    "A15517-e124870": [
      "simony"
    ],
    "A15517-e110730": [
      "love"
    ],
    "A15517-e103620": [
      "wit"
    ],
    "A15517-e115390": [
      "pleasure"
    ],
    "A15517-e114920": [
      "pomp"
    ],
    "A15517-e113150": [
      "nemo"
    ],
    "A15517-e109230": [
      "love"
    ],
    "A15517-e101180": [
      "wit"
    ],
    "A15517-e103000": [
      "will"
    ],
    "A15517-e114650": [
      "policy"
    ],
    "A15517-e124610": [
      "pleasure"
    ],
    "A15517-e104150": [
      "wit"
    ],
    "A15517-e102000": [
      "will"
    ],
    "A15517-e127450": [
      "pleasure"
    ],
    "A15517-e110000": [
      "fraud"
    ],
    "A15517-e110290": [
      "conscience"
    ],
    "A15517-e107790": [
      "simony"
    ],
    "A15517-e102940": [
      "wit"
    ],
    "A15517-e112200": [
      "pleasure"
    ],
    "A15517-e124590": [
      "simplicity"
    ],
    "A15517-e112790": [
      "conscience"
    ],
    "A15517-e111260": [
      "usury"
    ],
    "A15517-e113350": [
      "falsehood"
    ],
    "A15517-e106210": [
      "will"
    ],
    "A15517-e108250": [
      "usury"
    ],
    "A15517-e105740": [
      "simony"
    ],
    "A15517-e104470": [
      "wit"
    ],
    "A15517-e104530": [
      "simony"
    ],
    "A15517-e117250": [
      "policy"
    ],
    "A15517-e116790": [
      "diligence"
    ],
    "A15517-e123330": [
      "nemo"
    ],
    "A15517-e114560": [
      "policy"
    ],
    "A15517-e102380": [
      "will"
    ],
    "A15517-e105280": [
      "wealth"
    ],
    "A15517-e123870": [
      "fraud"
    ],
    "A15517-e102670": [
      "wit"
    ],
    "A15517-e125030": [
      "fraud"
    ],
    "A15517-e119810": [
      "policy"
    ],
    "A15517-e110570": [
      "dissimulation"
    ],
    "A15517-e113970": [
      "penury"
    ],
    "A15517-e114040": [
      "simplicity"
    ],
    "A15517-e101200": [
      "pomp"
    ],
    "A15517-e103460": [
      "wit"
    ],
    "A15517-e109100": [
      "lucre"
    ],
    "A15517-e118230": [
      "policy"
    ],
    "A15517-e113010": [
      "love"
    ],
    "A15517-e112920": [
      "falsehood"
    ],
    "A15517-e103520": [
      "simony"
    ],
    "A15517-e126410": [
      "fraud"
    ],
    "A15517-e106830": [
      "nemo"
    ],
    "A15517-e103930": [
      "simony"
    ],
    "A15517-e117100": [
      "pomp"
    ],
    "A15517-e104730": [
      "simony"
    ],
    "A15517-e120600": [
      "policy"
    ],
    "A15517-e105190": [
      "simony"
    ],
    "A15517-e127300": [
      "pleasure"
    ],
    "A15517-e110430": [
      "simony"
    ],
    "A15517-e122770": [
      "love"
    ],
    "A15517-e110370": [
      "fraud"
    ],
    "A15517-e102630": [
      "wealth"
    ],
    "A15517-e102140": [
      "will"
    ],
    "A15517-e108930": [
      "lucre"
    ],
    "A15517-e111220": [
      "conscience"
    ],
    "A15517-e108090": [
      "simplicity"
    ],
    "A15517-e114080": [
      "simony"
    ],
    "A15517-e122060": [
      "policy"
    ],
    "A15517-e125820": [
      "devotion"
    ],
    "A15517-e114710": [
      "policy"
    ],
    "A15517-e120330": [
      "fealty"
    ],
    "A15517-e106390": [
      "simony"
    ],
    "A15517-e127020": [
      "simplicity"
    ],
    "A15517-e120350": [
      "policy"
    ],
    "A15517-e118450": [
      "fealty"
    ],
    "A15517-e114610": [
      "pleasure"
    ],
    "A15517-e105860": [
      "penury"
    ],
    "A15517-e125350": [
      "desire"
    ],
    "A15517-e115500": [
      "pleasure"
    ],
    "A15517-e108310": [
      "fraud"
    ],
    "A15517-e112280": [
      "pleasure"
    ],
    "A15517-e119560": [
      "wit"
    ],
    "A15517-e111590": [
      "nemo"
    ],
    "A15517-e117740": [
      "fraud"
    ],
    "A15517-e104230": [
      "wealth"
    ],
    "A15517-e102770": [
      "will"
    ],
    "A15517-e113800": [
      "pleasure"
    ],
    "A15517-e120040": [
      "pride"
    ],
    "A15517-e121170": [
      "pleasure"
    ],
    "A15517-e102440": [
      "wit"
    ],
    "A15517-e116710": [
      "policy"
    ],
    "A15517-e105170": [
      "wealth"
    ],
    "A15517-e105920": [
      "penury"
    ],
    "A15517-e102300": [
      "will"
    ],
    "A15517-e116850": [
      "policy"
    ],
    "A15517-e125540": [
      "pomp"
    ],
    "A15517-e116020": [
      "policy"
    ],
    "A15517-e105480": [
      "wit"
    ],
    "A15517-e122450": [
      "pomp"
    ],
    "A15517-e106440": [
      "policy"
    ],
    "A15517-e127190": [
      "simony"
    ],
    "A15517-e114120": [
      "fraud"
    ],
    "A15517-e105900": [
      "will"
    ],
    "A15517-e105300": [
      "simony"
    ],
    "A15517-e103350": [
      "simony"
    ],
    "A15517-e106980": [
      "pleasure"
    ],
    "A15517-e113820": [
      "nemo"
    ],
    "A15517-e108910": [
      "love"
    ],
    "A15517-e118160": [
      "usury"
    ],
    "A15517-e121190": [
      "policy"
    ],
    "A15517-e123650": [
      "policy"
    ],
    "A15517-e114060": [
      "fraud"
    ],
    "A15517-e119880": [
      "pleasure"
    ],
    "A15517-e114140": [
      "penury"
    ],
    "A15517-e120430": [
      "fealty"
    ],
    "A15517-e121320": [
      "policy"
    ],
    "A15517-e126430": [
      "dissimulation"
    ],
    "A15517-e123310": [
      "pleasure"
    ],
    "A15517-e121260": [
      "pomp"
    ],
    "A15517-e101510": [
      "pomp"
    ],
    "A15517-e121790": [
      "pleasure"
    ],
    "A15517-e118630": [
      "wit"
    ],
    "A15517-e127220": [
      "pleasure"
    ],
    "A15517-e103890": [
      "simplicity"
    ],
    "A15517-e104130": [
      "simony"
    ],
    "A15517-e104870": [
      "will"
    ],
    "A15517-e116540": [
      "policy"
    ],
    "A15517-e115880": [
      "conscience"
    ],
    "A15517-e110350": [
      "simony"
    ],
    "A15517-e103370": [
      "wealth"
    ],
    "A15517-e110020": [
      "dissimulation"
    ],
    "A15517-e120370": [
      "fealty"
    ],
    "A15517-e117470": [
      "simplicity"
    ],
    "A15517-e101830": [
      "pleasure"
    ],
    "A15517-e110650": [
      "love"
    ],
    "A15517-e122850": [
      "nemo"
    ],
    "A15517-e117910": [
      "simplicity"
    ],
    "A15517-e104050": [
      "simony"
    ],
    "A15517-e125460": [
      "pomp"
    ],
    "A15517-e125520": [
      "delight"
    ],
    "A15517-e123740": [
      "policy"
    ],
    "A15517-e101810": [
      "pomp"
    ],
    "A15517-e125080": [
      "fraud"
    ],
    "A15517-e112380": [
      "nemo"
    ],
    "A15517-e102810": [
      "wit"
    ],
    "A15517-e124490": [
      "pleasure"
    ],
    "A15517-e123810": [
      "pleasure"
    ],
    "A15517-e123460": [
      "pomp"
    ],
    "A15517-e124710": [
      "simony"
    ],
    "A15517-e111170": [
      "conscience"
    ],
    "A15517-e124530": [
      "policy"
    ],
    "A15517-e110510": [
      "simplicity"
    ],
    "A15517-e104590": [
      "wit"
    ],
    "A15517-e123680": [
      "fraud"
    ],
    "A15517-e106360": [
      "wit"
    ],
    "A15517-e109380": [
      "love"
    ],
    "A15517-e108110": [
      "fraud"
    ],
    "A15517-e112320": [
      "policy"
    ],
    "A15517-e121340": [
      "fealty"
    ],
    "A15517-e118140": [
      "fraud"
    ],
    "A15517-e109540": [
      "love"
    ],
    "A15517-e117840": [
      "fraud"
    ],
    "A15517-e126880": [
      "simplicity"
    ],
    "A15517-e107530": [
      "pomp"
    ],
    "A15517-e123510": [
      "nemo"
    ],
    "A15517-e108050": [
      "simplicity"
    ],
    "A15517-e103990": [
      "simony"
    ],
    "A15517-e117780": [
      "simplicity"
    ],
    "A15517-e114440": [
      "pleasure"
    ],
    "A15517-e109850": [
      "lucre"
    ],
    "A15517-e105090": [
      "simony"
    ],
    "A15517-e116590": [
      "pomp"
    ],
    "A15517-e104890": [
      "simony"
    ],
    "A15517-e111050": [
      "simplicity"
    ],
    "A15517-e116520": [
      "pleasure"
    ],
    "A15517-e122920": [
      "conscience"
    ],
    "A15517-e124430": [
      "pleasure"
    ],
    "A15517-e115690": [
      "pleasure"
    ],
    "A15517-e125580": [
      "pleasure"
    ],
    "A15517-e110120": [
      "love"
    ],
    "A15517-e114770": [
      "policy"
    ],
    "A15517-e126130": [
      "delight"
    ],
    "A15517-e105340": [
      "simony"
    ],
    "A15517-e103390": [
      "simony"
    ],
    "A15517-e114160": [
      "simplicity"
    ],
    "A15517-e113560": [
      "pure-zeal"
    ],
    "A15517-e121410": [
      "fealty"
    ],
    "A15517-e126050": [
      "delight"
    ],
    "A15517-e117450": [
      "usury"
    ],
    "A15517-e123490": [
      "pleasure"
    ],
    "A15517-e127340": [
      "pomp"
    ],
    "A15517-e104030": [
      "will"
    ],
    "A15517-e102080": [
      "will"
    ],
    "A15517-e122020": [
      "pomp"
    ],
    "A15517-e105010": [
      "simony"
    ],
    "A15517-e113090": [
      "double-dealing"
    ],
    "A15517-e115040": [
      "nemo"
    ],
    "A15517-e113470": [
      "industry"
    ],
    "A15517-e101010": [
      "pomp"
    ],
    "A15517-e119110": [
      "policy"
    ],
    "A15517-e112020": [
      "nemo"
    ],
    "A15517-e115420": [
      "nemo"
    ],
    "A15517-e102180": [
      "wit"
    ],
    "A15517-e108970": [
      "love"
    ],
    "A15517-e111740": [
      "nemo"
    ],
    "A15517-e124510": [
      "simplicity"
    ],
    "A15517-e110530": [
      "usury"
    ],
    "A15517-e115950": [
      "conscience"
    ],
    "A15517-e125440": [
      "desire"
    ],
    "A15517-e121710": [
      "policy"
    ],
    "A15517-e104690": [
      "simony"
    ],
    "A15517-e110210": [
      "conscience"
    ],
    "A15517-e103500": [
      "will"
    ],
    "A15517-e106810": [
      "policy"
    ],
    "A15517-e124450": [
      "policy"
    ],
    "A15517-e110450": [
      "conscience"
    ],
    "A15517-e126100": [
      "desire"
    ],
    "A15517-e104550": [
      "wit"
    ],
    "A15517-e117180": [
      "pleasure"
    ],
    "A15517-e106320": [
      "wit"
    ],
    "A15517-e102120": [
      "will"
    ],
    "A15517-e112340": [
      "pomp"
    ],
    "A15517-e115230": [
      "pomp"
    ],
    "A15517-e118060": [
      "dissimulation"
    ],
    "A15517-e107130": [
      "policy"
    ],
    "A15517-e108130": [
      "simplicity"
    ],
    "A15517-e104710": [
      "wit"
    ],
    "A15517-e117820": [
      "simplicity"
    ],
    "A15517-e103970": [
      "wealth"
    ],
    "A15517-e108070": [
      "usury"
    ],
    "A15517-e123840": [
      "pomp"
    ],
    "A15517-e122940": [
      "pleasure"
    ],
    "A15517-e103060": [
      "wit"
    ],
    "A15517-e105110": [
      "will"
    ],
    "A15517-e107110": [
      "nemo"
    ],
    "A15517-e108890": [
      "conscience"
    ],
    "A15517-e114750": [
      "pomp"
    ],
    "A15517-e113620": [
      "nemo"
    ],
    "A15517-e113540": [
      "nemo"
    ],
    "A15517-e126070": [
      "devotion"
    ],
    "A15517-e119510": [
      "fealty"
    ],
    "A15517-e115320": [
      "conscience"
    ],
    "A15517-e124360": [
      "fraud"
    ],
    "A15517-e102790": [
      "wealth"
    ],
    "A15517-e117760": [
      "usury"
    ],
    "A15517-e124170": [
      "usury"
    ],
    "A15517-e108330": [
      "simplicity"
    ],
    "A15517-e113270": [
      "nemo"
    ],
    "A15517-e103330": [
      "wealth"
    ],
    "A15517-e111820": [
      "nemo"
    ],
    "A15517-e110820": [
      "simplicity"
    ],
    "A15517-e109950": [
      "conscience"
    ],
    "A15517-e111120": [
      "lucre"
    ],
    "A15517-e102460": [
      "will"
    ],
    "A15517-e115970": [
      "nemo"
    ],
    "A15517-e122000": [
      "fealty"
    ],
    "A15517-e104410": [
      "simony"
    ],
    "A15517-e127170": [
      "pleasure"
    ],
    "A15517-e114100": [
      "penury"
    ],
    "A15517-e106960": [
      "nemo"
    ],
    "A15517-e125620": [
      "policy"
    ],
    "A15517-e112000": [
      "policy"
    ],
    "A15517-e106180": [
      "simony"
    ],
    "A15517-e103720": [
      "wealth"
    ],
    "A15517-e111700": [
      "love"
    ],
    "A15517-e124790": [
      "simony"
    ],
    "A15517-e102890": [
      "wit"
    ],
    "A15517-e107750": [
      "fraud"
    ],
    "A15517-e123290": [
      "pomp"
    ],
    "A15517-e110250": [
      "usury"
    ],
    "A15517-e124270": [
      "pleasure"
    ],
    "A15517-e126210": [
      "simplicity"
    ],
    "A15517-e125400": [
      "devotion"
    ],
    "A15517-e105050": [
      "simony"
    ],
    "A15517-e102280": [
      "wit"
    ],
    "A15517-e123200": [
      "policy"
    ],
    "A15517-e106700": [
      "pleasure"
    ],
    "A15517-e117490": [
      "usury"
    ],
    "A15517-e119900": [
      "wit"
    ],
    "A15517-e104070": [
      "will"
    ],
    "A15517-e104930": [
      "simony"
    ],
    "A15517-e107090": [
      "pleasure"
    ],
    "A15517-e118650": [
      "simplicity"
    ],
    "A15517-e127240": [
      "simplicity"
    ],
    "A15517-e117620": [
      "fraud"
    ],
    "A15517-e104110": [
      "will"
    ],
    "A15517-e114240": [
      "penury"
    ],
    "A15517-e122220": [
      "pleasure"
    ],
    "A15517-e114290": [
      "simplicity"
    ],
    "A15517-e111670": [
      "nemo"
    ],
    "A15517-e119990": [
      "fealty"
    ],
    "A15517-e112160": [
      "policy"
    ],
    "A15517-e108400": [
      "conscience"
    ],
    "A15517-e108290": [
      "simplicity"
    ],
    "A15517-e108010": [
      "fraud"
    ],
    "A15517-e121930": [
      "fealty"
    ],
    "A15517-e103810": [
      "simony"
    ],
    "A15517-e108150": [
      "dissimulation"
    ],
    "A15517-e122960": [
      "policy"
    ],
    "A15517-e123700": [
      "policy"
    ],
    "A15517-e109890": [
      "lucre"
    ],
    "A15517-e117800": [
      "usury"
    ],
    "A15517-e115790": [
      "conscience"
    ],
    "A15517-e107920": [
      "simony"
    ],
    "A15517-e123790": [
      "dissimulation"
    ],
    "A15517-e113760": [
      "policy"
    ],
    "A15517-e119240": [
      "fealty"
    ],
    "A15517-e107480": [
      "nemo"
    ],
    "A15517-e122320": [
      "pleasure"
    ],
    "A15517-e102510": [
      "will"
    ],
    "A15517-e112360": [
      "pleasure"
    ],
    "A15517-e118040": [
      "usury"
    ],
    "A15517-e104390": [
      "wit"
    ],
    "A15517-e116690": [
      "conscience"
    ],
    "A15517-e124470": [
      "simplicity"
    ],
    "A15517-e105500": [
      "will"
    ],
    "A15517-e111150": [
      "usury"
    ],
    "A15517-e103180": [
      "wit"
    ],
    "A15517-e109590": [
      "lucre"
    ],
    "A15517-e113380": [
      "nemo"
    ],
    "A15517-e100700": [
      "policy"
    ],
    "A15517-e119460": [
      "fealty"
    ],
    "A15517-e109300": [
      "love"
    ],
    "A15517-e118500": [
      "constable"
    ],
    "A15517-e124650": [
      "policy"
    ],
    "A15517-e121830": [
      "pomp"
    ],
    "A15517-e110230": [
      "simplicity"
    ],
    "A15517-e102420": [
      "will"
    ],
    "A15517-e122040": [
      "fealty"
    ],
    "A15517-e110790": [
      "usury"
    ],
    "A15517-e109010": [
      "conscience"
    ],
    "A15517-e114960": [
      "pleasure"
    ],
    "A15517-e104840": [
      "simony"
    ],
    "A15517-e111510": [
      "usury"
    ],
    "A15517-e124320": [
      "simplicity"
    ],
    "A15517-e124830": [
      "simony"
    ],
    "A15517-e121980": [
      "policy"
    ],
    "A15517-e105030": [
      "will"
    ],
    "A15517-e122880": [
      "lucre"
    ],
    "A15517-e106610": [
      "pomp"
    ],
    "A15517-e126930": [
      "pleasure"
    ],
    "A15517-e127130": [
      "pleasure"
    ],
    "A15517-e118000": [
      "usury"
    ],
    "A15517-e123020": [
      "nemo"
    ],
    "A15517-e111480": [
      "fraud"
    ],
    "A15517-e118020": [
      "fraud"
    ],
    "A15517-e102980": [
      "wit"
    ],
    "A15517-e103540": [
      "wit"
    ],
    "A15517-e117680": [
      "usury"
    ],
    "A15517-e104250": [
      "wit"
    ],
    "A15517-e105970": [
      "wit"
    ],
    "A15517-e114790": [
      "nemo"
    ],
    "A15517-e103250": [
      "wit"
    ],
    "A15517-e107460": [
      "pomp"
    ],
    "A15517-e113930": [
      "penury"
    ],
    "A15517-e114260": [
      "fraud"
    ],
    "A15517-e101390": [
      "policy"
    ],
    "A15517-e126310": [
      "diligence"
    ],
    "A15517-e104750": [
      "wit"
    ],
    "A15517-e112400": [
      "policy"
    ],
    "A15517-e109870": [
      "simony"
    ],
    "A15517-e101770": [
      "policy"
    ],
    "A15517-e105670": [
      "wealth"
    ],
    "A15517-e123770": [
      "pleasure"
    ],
    "A15517-e116050": [
      "diligence"
    ],
    "A15517-e125370": [
      "delight"
    ],
    "A15517-e119730": [
      "fealty"
    ],
    "A15517-e110490": [
      "fraud"
    ],
    "A15517-e126270": [
      "diligence"
    ],
    "A15517-e121210": [
      "fealty"
    ],
    "A15517-e117310": [
      "simplicity"
    ],
    "A15517-e117590": [
      "simony"
    ],
    "A15517-e109410": [
      "conscience"
    ],
    "A15517-e120390": [
      "policy"
    ],
    "A15517-e114310": [
      "penury"
    ],
    "A15517-e109980": [
      "dissimulation"
    ],
    "A15517-e104820": [
      "wit"
    ],
    "A15517-e116650": [
      "nemo"
    ],
    "A15517-e107000": [
      "nemo"
    ],
    "A15517-e105130": [
      "simony"
    ],
    "A15517-e102340": [
      "wealth"
    ],
    "A15517-e102400": [
      "wit"
    ],
    "A15517-e104570": [
      "simony"
    ],
    "A15517-e106340": [
      "simony"
    ],
    "A15517-e114940": [
      "policy"
    ],
    "A15517-e127150": [
      "simony"
    ],
    "A15517-e124630": [
      "simplicity"
    ],
    "A15517-e110410": [
      "conscience"
    ],
    "A15517-e113730": [
      "nemo"
    ],
    "A15517-e126950": [
      "simplicity"
    ],
    "A15517-e109070": [
      "love"
    ],
    "A15517-e111770": [
      "lucre"
    ],
    "A15517-e126570": [
      "nemo"
    ],
    "A15517-e112440": [
      "pleasure"
    ],
    "A15517-e113110": [
      "nemo"
    ],
    "A15517-e103560": [
      "simony"
    ],
    "A15517-e105690": [
      "wit"
    ],
    "A15517-e101140": [
      "pomp"
    ],
    "A15517-e103270": [
      "simony"
    ],
    "A15517-e115260": [
      "pleasure"
    ],
    "A15517-e123040": [
      "policy"
    ],
    "A15517-e119530": [
      "policy"
    ],
    "A15517-e118480": [
      "simplicity"
    ],
    "A15517-e119400": [
      "fealty"
    ],
    "A15517-e102960": [
      "wealth"
    ],
    "A15517-e117960": [
      "usury"
    ],
    "A15517-e108190": [
      "simony"
    ],
    "A15517-e103870": [
      "wealth"
    ],
    "A15517-e118790": [
      "policy"
    ],
    "A15517-e117660": [
      "fraud"
    ],
    "A15517-e104770": [
      "simony"
    ],
    "A15517-e122800": [
      "conscience"
    ],
    "A15517-e121040": [
      "policy"
    ],
    "A15517-e118610": [
      "simplicity"
    ],
    "A15517-e115860": [
      "pleasure"
    ],
    "A15517-e110330": [
      "usury"
    ],
    "A15517-e105640": [
      "simony"
    ],
    "A15517-e125920": [
      "policy"
    ],
    "A15517-e110470": [
      "simplicity"
    ],
    "A15517-e126250": [
      "simplicity"
    ],
    "A15517-e125730": [
      "desire"
    ],
    "A15517-e125880": [
      "policy"
    ],
    "A15517-e120670": [
      "fealty"
    ],
    "A15517-e117570": [
      "usury"
    ],
    "A15517-e102250": [
      "will"
    ],
    "A15517-e115200": [
      "policy"
    ],
    "A15517-e107070": [
      "pomp"
    ],
    "A15517-e117640": [
      "simplicity"
    ],
    "A15517-e107730": [
      "simplicity"
    ],
    "A15517-e126230": [
      "diligence"
    ],
    "A15517-e116730": [
      "diligence"
    ],
    "A15517-e114220": [
      "fraud"
    ],
    "A15517-e122430": [
      "pride"
    ],
    "A15517-e114330": [
      "simplicity"
    ],
    "A15517-e104210": [
      "simony"
    ],
    "A15517-e109830": [
      "fraud"
    ],
    "A15517-e104090": [
      "simony"
    ],
    "A15517-e102320": [
      "wit"
    ],
    "A15517-e124290": [
      "pomp"
    ],
    "A15517-e125560": [
      "desire"
    ],
    "A15517-e105320": [
      "wit"
    ],
    "A15517-e101110": [
      "pleasure"
    ],
    "A15517-e103210": [
      "simony"
    ],
    "A15517-e121300": [
      "fealty"
    ],
    "A15517-e112180": [
      "pomp"
    ],
    "A15517-e106060": [
      "simony"
    ],
    "A15517-e107550": [
      "nemo"
    ],
    "A15517-e115810": [
      "pleasure"
    ],
    "A15517-e103910": [
      "will"
    ],
    "A15517-e121910": [
      "pleasure"
    ],
    "A15517-e112460": [
      "nemo"
    ],
    "A15517-e121360": [
      "policy"
    ],
    "A15517-e118530": [
      "pomp"
    ],
    "A15517-e117940": [
      "fraud"
    ],
    "A15517-e120010": [
      "fealty"
    ],
    "A15517-e123590": [
      "pomp"
    ],
    "A15517-e115840": [
      "conscience"
    ],
    "A15517-e107900": [
      "fraud"
    ],
    "A15517-e108770": [
      "sorrow"
    ],
    "A15517-e104670": [
      "wit"
    ],
    "A15517-e122340": [
      "policy"
    ],
    "A15517-e115900": [
      "nemo"
    ],
    "A15517-e122520": [
      "policy"
    ],
    "A15517-e116360": [
      "conscience"
    ],
    "A15517-e109510": [
      "conscience"
    ],
    "A15517-e108950": [
      "conscience"
    ],
    "A15517-e103850": [
      "wit"
    ],
    "A15517-e123720": [
      "fraud"
    ]
  },
  "changes": [
    {
      "when": "2022-07-04",
      "text": "(Luca Giovannini) Fixed speaker tags and particDesc"
    }
  ]
}
